rpmfile/__init__.py
rpmfile/__main__.py
rpmfile/cli.py
rpmfile/cpiofile.py
rpmfile/errors.py
rpmfile/headers.py
rpmfile/io_extra.py
rpmfile/rpmdefs.py
rpmfile-2.0.0.dist-info/LICENSE
rpmfile-2.0.0.dist-info/METADATA
rpmfile-2.0.0.dist-info/WHEEL
rpmfile-2.0.0.dist-info/entry_points.txt
rpmfile-2.0.0.dist-info/top_level.txt
rpmfile-2.0.0.dist-info/RECORD
