Metadata-Version: 2.1
Name: rpmfile
Version: 2.0.0
Summary: Read rpm archive files
Home-page: https://github.com/srossross/rpmfile
Author: Sean Ross-Ross
Author-email: srossross@gmail.com
License: MIT
Classifier: Intended Audience :: Developers
Classifier: License :: OSI Approved :: MIT License
Classifier: Natural Language :: English
Classifier: Operating System :: OS Independent
Classifier: Programming Language :: Python :: 2.6
Classifier: Programming Language :: Python :: 2.7
Classifier: Programming Language :: Python :: 3.4
Classifier: Programming Language :: Python :: 3.5
Classifier: Programming Language :: Python :: 3.6
Classifier: Programming Language :: Python :: 3.7
Classifier: Programming Language :: Python :: 3.8
License-File: LICENSE
Provides-Extra: zstd
Requires-Dist: zstandard >=0.13.0 ; extra == 'zstd'
